{
  "response": [
    {
      "oem": "Xiaomi",
      "name": "Mi MIX 3 5G",
      "codename": "andromeda",
      "filename": "Havoc-OS-v3.9-20200916-andromeda-Official.zip",
      "version": "3.9",
      "romtype": "Official",
      "variant": "Vanilla",
      "maintainer": "Nicholas Magill (Inkypen)",
      "size": "1099769738",
      "datetime": 1600247275,
      "id": "f6a60fdc697e52d60c10431eeda5d60cc7d0498562221277b1329062fcd8efc0",
      "url": "https://sourceforge.net/projects/havoc-os/files/andromeda/Havoc-OS-v3.9-20200916-andromeda-Official.zip/download",
      "group": "https://t.me/havoc_andromeda",
      "changelog": ""
    }
  ]
}
