{
  "oem":"Xiaomi",
  "name":"Xiaomi Redmi K30 / Poco X2",
  "codename":"phoenix",
  "filename":"Havoc-OS-v4.19-20220806-phoenix-Official.zip",
  "version":"4.19",
  "romtype":"Official",
  "variant":"Vanilla",
  "maintainer":"Abubakar Yagoub",
  "username":"Blacksuan19",
  "size":1062041152,
  "datetime":1659769892,
  "filehash":"9e1212495ca7eb3eeec5da79437a7220",
  "id":"7fa2259e1fe139799d33f27cf3b059f488e736455da44642d9635b40956f6832",
  "url":"https://download.havoc-os.com/phoenix/Havoc-OS-v4.19-20220806-phoenix-Official.zip",
  "group":"https://t.me/+vrYDRknBKosxMDk1"
}
